{"v":"5.4.4","fr":60,"ip":0,"op":288,"w":300,"h":300,"nm":"Comp 4","ddd":0,"assets":[],"layers":[{"ddd":0,"ind":1,"ty":1,"nm":"White Solid 1","sr":1,"ks":{"o":{"a":0,"k":100,"ix":11},"r":{"a":0,"k":0,"ix":10},"p":{"a":0,"k":[170,174,0],"ix":2},"a":{"a":0,"k":[170,174,0],"ix":1},"s":{"a":0,"k":[100,100,100],"ix":6}},"ao":0,"hasMask":true,"masksProperties":[{"inv":false,"mode":"s","pt":{"a":0,"k":{"i":[[81.333,0],[0,-81.333],[-81.333,0],[0,81.333]],"o":[[-81.333,0],[0,81.333],[81.333,0],[0,-81.333]],"v":[[151.266,2],[4,149.266],[151.266,296.531],[298.531,149.266]],"c":true},"ix":1},"o":{"a":0,"k":100,"ix":3},"x":{"a":0,"k":0,"ix":4},"nm":"Mask 1"}],"sw":300,"sh":300,"sc":"#ffffff","ip":0,"op":288,"st":0,"bm":0},{"ddd":0,"ind":2,"ty":4,"nm":"Shape Layer 1","sr":1,"ks":{"o":{"a":0,"k":100,"ix":11},"r":{"a":0,"k":0,"ix":10},"p":{"a":0,"k":[150,150,0],"ix":2},"a":{"a":0,"k":[0,0,0],"ix":1},"s":{"a":0,"k":[100,100,100],"ix":6}},"ao":0,"shapes":[],"ip":0,"op":288,"st":0,"bm":0},{"ddd":0,"ind":3,"ty":4,"nm":"Ray","sr":1,"ks":{"o":{"a":1,"k":[{"i":{"x":[0.833],"y":[0.833]},"o":{"x":[0.167],"y":[0.167]},"t":2,"s":[0],"e":[100]},{"i":{"x":[0.833],"y":[0.833]},"o":{"x":[0.167],"y":[0.167]},"t":7,"s":[100],"e":[100]},{"i":{"x":[0.833],"y":[0.833]},"o":{"x":[0.167],"y":[0.167]},"t":82,"s":[100],"e":[0]},{"i":{"x":[0.833],"y":[0.833]},"o":{"x":[0.167],"y":[0.167]},"t":89,"s":[0],"e":[0]},{"i":{"x":[0.833],"y":[0.833]},"o":{"x":[0.167],"y":[0.167]},"t":155,"s":[0],"e":[100]},{"i":{"x":[0.833],"y":[0.833]},"o":{"x":[0.167],"y":[0.167]},"t":160,"s":[100],"e":[100]},{"i":{"x":[0.833],"y":[0.833]},"o":{"x":[0.167],"y":[0.167]},"t":235,"s":[100],"e":[0]},{"t":242}],"ix":11},"r":{"a":0,"k":0,"ix":10},"p":{"a":0,"k":[150,150,0],"ix":2},"a":{"a":0,"k":[0,0,0],"ix":1},"s":{"a":0,"k":[100,100,100],"ix":6}},"ao":0,"shapes":[{"ty":"gr","it":[{"ind":0,"ty":"sh","ix":1,"ks":{"a":1,"k":[{"i":{"x":0.999,"y":1},"o":{"x":1,"y":0},"t":7,"s":[{"i":[[0,0],[0,0]],"o":[[0,0],[0,0]],"v":[[41.5,-126.5],[41.438,-126.438]],"c":false}],"e":[{"i":[[0,0],[0,0]],"o":[[0,0],[0,0]],"v":[[41.5,-126.5],[31.5,-117.562]],"c":false}]},{"i":{"x":0,"y":1},"o":{"x":0.001,"y":0},"t":44,"s":[{"i":[[0,0],[0,0]],"o":[[0,0],[0,0]],"v":[[41.5,-126.5],[31.5,-117.562]],"c":false}],"e":[{"i":[[0,0],[0,0]],"o":[[0,0],[0,0]],"v":[[31.5,-117.547],[31.5,-117.562]],"c":false}]},{"i":{"x":0.833,"y":1},"o":{"x":0.167,"y":0},"t":103,"s":[{"i":[[0,0],[0,0]],"o":[[0,0],[0,0]],"v":[[31.5,-117.547],[31.5,-117.562]],"c":false}],"e":[{"i":[[0,0],[0,0]],"o":[[0,0],[0,0]],"v":[[41.5,-126.5],[41.438,-126.438]],"c":false}]},{"i":{"x":0.999,"y":1},"o":{"x":1,"y":0},"t":160,"s":[{"i":[[0,0],[0,0]],"o":[[0,0],[0,0]],"v":[[41.5,-126.5],[41.438,-126.438]],"c":false}],"e":[{"i":[[0,0],[0,0]],"o":[[0,0],[0,0]],"v":[[41.5,-126.5],[31.5,-117.562]],"c":false}]},{"i":{"x":0,"y":1},"o":{"x":0.001,"y":0},"t":197,"s":[{"i":[[0,0],[0,0]],"o":[[0,0],[0,0]],"v":[[41.5,-126.5],[31.5,-117.562]],"c":false}],"e":[{"i":[[0,0],[0,0]],"o":[[0,0],[0,0]],"v":[[31.5,-117.547],[31.5,-117.562]],"c":false}]},{"t":256}],"ix":2},"nm":"Path 1","mn":"ADBE Vector Shape - Group","hd":false},{"ty":"st","c":{"a":0,"k":[0.992156862745,0.854901960784,0.117647058824,1],"ix":3},"o":{"a":0,"k":100,"ix":4},"w":{"a":0,"k":4,"ix":5},"lc":2,"lj":1,"ml":4,"bm":0,"nm":"Stroke 1","mn":"ADBE Vector Graphic - Stroke","hd":false},{"ty":"gr","it":[{"ind":0,"ty":"sh","ix":1,"ks":{"a":1,"k":[{"i":{"x":0.999,"y":1},"o":{"x":1,"y":0},"t":7,"s":[{"i":[[0,0],[0,0]],"o":[[0,0],[0,0]],"v":[[41.5,-126.5],[41.438,-126.438]],"c":false}],"e":[{"i":[[0,0],[0,0]],"o":[[0,0],[0,0]],"v":[[41.5,-126.5],[31.5,-117.562]],"c":false}]},{"i":{"x":0,"y":1},"o":{"x":0.001,"y":0},"t":44,"s":[{"i":[[0,0],[0,0]],"o":[[0,0],[0,0]],"v":[[41.5,-126.5],[31.5,-117.562]],"c":false}],"e":[{"i":[[0,0],[0,0]],"o":[[0,0],[0,0]],"v":[[31.5,-117.547],[31.5,-117.562]],"c":false}]},{"i":{"x":0.833,"y":1},"o":{"x":0.167,"y":0},"t":103,"s":[{"i":[[0,0],[0,0]],"o":[[0,0],[0,0]],"v":[[31.5,-117.547],[31.5,-117.562]],"c":false}],"e":[{"i":[[0,0],[0,0]],"o":[[0,0],[0,0]],"v":[[41.5,-126.5],[41.438,-126.438]],"c":false}]},{"i":{"x":0.999,"y":1},"o":{"x":1,"y":0},"t":160,"s":[{"i":[[0,0],[0,0]],"o":[[0,0],[0,0]],"v":[[41.5,-126.5],[41.438,-126.438]],"c":false}],"e":[{"i":[[0,0],[0,0]],"o":[[0,0],[0,0]],"v":[[41.5,-126.5],[31.5,-117.562]],"c":false}]},{"i":{"x":0,"y":1},"o":{"x":0.001,"y":0},"t":197,"s":[{"i":[[0,0],[0,0]],"o":[[0,0],[0,0]],"v":[[41.5,-126.5],[31.5,-117.562]],"c":false}],"e":[{"i":[[0,0],[0,0]],"o":[[0,0],[0,0]],"v":[[31.5,-117.547],[31.5,-117.562]],"c":false}]},{"t":256}],"ix":2},"nm":"Path 1","mn":"ADBE Vector Shape - Group","hd":false},{"ty":"st","c":{"a":0,"k":[0.992156862745,0.854901960784,0.117647058824,1],"ix":3},"o":{"a":0,"k":100,"ix":4},"w":{"a":0,"k":4,"ix":5},"lc":2,"lj":1,"ml":4,"bm":0,"nm":"Stroke 1","mn":"ADBE Vector Graphic - Stroke","hd":false},{"ty":"gr","it":[{"ind":0,"ty":"sh","ix":1,"ks":{"a":1,"k":[{"i":{"x":0.999,"y":1},"o":{"x":1,"y":0},"t":7,"s":[{"i":[[0,0],[0,0]],"o":[[0,0],[0,0]],"v":[[41.5,-126.5],[41.438,-126.438]],"c":false}],"e":[{"i":[[0,0],[0,0]],"o":[[0,0],[0,0]],"v":[[41.5,-126.5],[31.5,-117.562]],"c":false}]},{"i":{"x":0,"y":1},"o":{"x":0.001,"y":0},"t":44,"s":[{"i":[[0,0],[0,0]],"o":[[0,0],[0,0]],"v":[[41.5,-126.5],[31.5,-117.562]],"c":false}],"e":[{"i":[[0,0],[0,0]],"o":[[0,0],[0,0]],"v":[[31.5,-117.547],[31.5,-117.562]],"c":false}]},{"i":{"x":0.833,"y":1},"o":{"x":0.167,"y":0},"t":103,"s":[{"i":[[0,0],[0,0]],"o":[[0,0],[0,0]],"v":[[31.5,-117.547],[31.5,-117.562]],"c":false}],"e":[{"i":[[0,0],[0,0]],"o":[[0,0],[0,0]],"v":[[41.5,-126.5],[41.438,-126.438]],"c":false}]},{"i":{"x":0.999,"y":1},"o":{"x":1,"y":0},"t":160,"s":[{"i":[[0,0],[0,0]],"o":[[0,0],[0,0]],"v":[[41.5,-126.5],[41.438,-126.438]],"c":false}],"e":[{"i":[[0,0],[0,0]],"o":[[0,0],[0,0]],"v":[[41.5,-126.5],[31.5,-117.562]],"c":false}]},{"i":{"x":0,"y":1},"o":{"x":0.001,"y":0},"t":197,"s":[{"i":[[0,0],[0,0]],"o":[[0,0],[0,0]],"v":[[41.5,-126.5],[31.5,-117.562]],"c":false}],"e":[{"i":[[0,0],[0,0]],"o":[[0,0],[0,0]],"v":[[31.5,-117.547],[31.5,-117.562]],"c":false}]},{"t":256}],"ix":2},"nm":"Path 1","mn":"ADBE Vector Shape - Group","hd":false},{"ty":"st","c":{"a":0,"k":[0.992156862745,0.854901960784,0.117647058824,1],"ix":3},"o":{"a":0,"k":100,"ix":4},"w":{"a":0,"k":4,"ix":5},"lc":2,"lj":1,"ml":4,"bm":0,"nm":"Stroke 1","mn":"ADBE Vector Graphic - Stroke","hd":false},{"ty":"tr","p":{"a":0,"k":[78.283,24.674],"ix":2},"a":{"a":0,"k":[0,0],"ix":1},"s":{"a":0,"k":[100,100],"ix":3},"r":{"a":0,"k":-24.308,"ix":6},"o":{"a":0,"k":100,"ix":7},"sk":{"a":0,"k":0,"ix":4},"sa":{"a":0,"k":0,"ix":5},"nm":"Transform"}],"nm":"Shape 1","np":3,"cix":2,"bm":0,"ix":4,"mn":"ADBE Vector Group","hd":false},{"ty":"tr","p":{"a":0,"k":[78.283,24.674],"ix":2},"a":{"a":0,"k":[0,0],"ix":1},"s":{"a":0,"k":[100,100],"ix":3},"r":{"a":0,"k":-24.308,"ix":6},"o":{"a":0,"k":100,"ix":7},"sk":{"a":0,"k":0,"ix":4},"sa":{"a":0,"k":0,"ix":5},"nm":"Transform"}],"nm":"Shape 1","np":4,"cix":2,"bm":0,"ix":4,"mn":"ADBE Vector Group","hd":false},{"ty":"tr","p":{"a":0,"k":[0,0],"ix":2},"a":{"a":0,"k":[0,0],"ix":1},"s":{"a":0,"k":[100,100],"ix":3},"r":{"a":0,"k":0,"ix":6},"o":{"a":0,"k":100,"ix":7},"sk":{"a":0,"k":0,"ix":4},"sa":{"a":0,"k":0,"ix":5},"nm":"Transform"}],"nm":"Shape 1","np":4,"cix":2,"bm":0,"ix":1,"mn":"ADBE Vector Group","hd":false}],"ip":0,"op":288,"st":0,"bm":0},{"ddd":0,"ind":4,"ty":4,"nm":"Cloud","sr":1,"ks":{"o":{"a":0,"k":100,"ix":11},"r":{"a":0,"k":0,"ix":10},"p":{"a":1,"k":[{"i":{"x":0.833,"y":0.833},"o":{"x":0.167,"y":0.167},"t":0,"s":[364.974,143.744,0],"e":[114.974,389.744,0],"to":[-41.667,41,0],"ti":[41.667,-41,0]},{"t":212}],"ix":2},"a":{"a":0,"k":[361.974,443.744,0],"ix":1},"s":{"a":0,"k":[299.751,299.751,100],"ix":6}},"ao":0,"shapes":[{"ty":"gr","it":[{"ind":0,"ty":"sh","ix":1,"ks":{"a":0,"k":{"i":[[5.922,0],[1.782,-6.832],[0,-1.386],[0,0],[1.089,-0.297],[0,-5.347],[-6.535,0],[-2.178,2.376],[-0.495,1.782],[-1.485,-0.099],[0,0],[-2.681,4.924],[0,0]],"o":[[-7.426,0],[-0.297,1.287],[0,0],[-1.188,0],[-4.852,1.485],[0,6.535],[3.564,0],[1.188,-1.287],[1.386,0.495],[0,0],[5.922,0],[0,0],[-2.681,-4.826]],"v":[[369.165,423.943],[353.819,435.824],[353.324,439.784],[352.829,439.784],[349.364,440.279],[340.948,451.665],[352.829,463.546],[361.74,459.586],[364.314,454.834],[368.67,455.626],[369.165,455.626],[383,447.454],[383,432.016]],"c":true},"ix":2},"nm":"Path 1","mn":"ADBE Vector Shape - Group","hd":false},{"ty":"fl","c":{"a":0,"k":[0.596078431373,0.83137254902,0.925490196078,1],"ix":4},"o":{"a":0,"k":100,"ix":5},"r":1,"bm":0,"nm":"Fill 1","mn":"ADBE Vector Graphic - Fill","hd":false},{"ty":"tr","p":{"a":0,"k":[0,0],"ix":2},"a":{"a":0,"k":[0,0],"ix":1},"s":{"a":0,"k":[100,100],"ix":3},"r":{"a":0,"k":0,"ix":6},"o":{"a":0,"k":100,"ix":7},"sk":{"a":0,"k":0,"ix":4},"sa":{"a":0,"k":0,"ix":5},"nm":"Transform"}],"nm":"Group 1","np":2,"cix":2,"bm":0,"ix":1,"mn":"ADBE Vector Group","hd":false}],"ip":0,"op":288,"st":0,"bm":0},{"ddd":0,"ind":5,"ty":4,"nm":"Sun","sr":1,"ks":{"o":{"a":0,"k":100,"ix":11},"r":{"a":0,"k":16.107,"ix":10},"p":{"a":0,"k":[243,-4,0],"ix":2},"a":{"a":0,"k":[81.843,-127.11,0],"ix":1},"s":{"a":0,"k":[100,100,100],"ix":6}},"ao":0,"shapes":[{"ty":"gr","it":[{"d":1,"ty":"el","s":{"a":0,"k":[91.355,91.355],"ix":2},"p":{"a":0,"k":[0,0],"ix":3},"nm":"Ellipse Path 1","mn":"ADBE Vector Shape - Ellipse","hd":false},{"ty":"fl","c":{"a":0,"k":[0.992156862745,0.854901960784,0.117647058824,1],"ix":4},"o":{"a":0,"k":100,"ix":5},"r":1,"bm":0,"nm":"Fill 1","mn":"ADBE Vector Graphic - Fill","hd":false},{"ty":"tr","p":{"a":0,"k":[77.678,-127.322],"ix":2},"a":{"a":0,"k":[0,0],"ix":1},"s":{"a":0,"k":[100,100],"ix":3},"r":{"a":0,"k":0,"ix":6},"o":{"a":0,"k":100,"ix":7},"sk":{"a":0,"k":0,"ix":4},"sa":{"a":0,"k":0,"ix":5},"nm":"Transform"}],"nm":"Ellipse 1","np":3,"cix":2,"bm":0,"ix":1,"mn":"ADBE Vector Group","hd":false}],"ip":0,"op":288,"st":0,"bm":0},{"ddd":0,"ind":6,"ty":4,"nm":"Plane","sr":1,"ks":{"o":{"a":0,"k":100,"ix":11},"r":{"a":0,"k":0,"ix":10},"p":{"a":1,"k":[{"i":{"x":0.4,"y":1},"o":{"x":0.6,"y":0},"t":0,"s":[147.957,168.546,0],"e":[151.957,172.546,0],"to":[0.667,0.667,0],"ti":[-0.007,0.008,0]},{"i":{"x":0.4,"y":1},"o":{"x":0.6,"y":0},"t":86,"s":[151.957,172.546,0],"e":[148,168.5,0],"to":[0.007,-0.008,0],"ti":[0.659,0.674,0]},{"t":288}],"ix":2},"a":{"a":0,"k":[407.957,422.546,0],"ix":1},"s":{"a":0,"k":[259.077,259.077,100],"ix":6}},"ao":0,"shapes":[{"ty":"gr","it":[{"ind":0,"ty":"sh","ix":1,"ks":{"a":0,"k":{"i":[[-0.495,-0.396],[-0.396,0],[-0.198,0.099],[0,0],[-0.198,0.297],[0,0],[0,0],[1.584,3.663],[3.069,0],[0.99,-0.396],[0,0],[0,0],[0.396,-0.198],[0,0],[0.099,-0.495],[-0.297,-0.297],[0,0],[-0.495,0.198],[0,0],[0,0]],"o":[[0.297,0.198],[0.198,0],[0,0],[0.297,-0.099],[0,0],[0,0],[3.762,-1.584],[-1.188,-2.772],[-0.99,0],[0,0],[0,0],[-0.396,-0.198],[0,0],[-0.495,0.198],[-0.099,0.495],[0,0],[0.396,0.396],[0,0],[0,0],[-0.198,0.594]],"v":[[399.71,446.457],[400.7,446.853],[401.393,446.655],[413.175,440.814],[413.868,440.121],[425.354,417.249],[438.621,412.299],[442.581,402.794],[435.75,398.24],[432.878,398.834],[393.373,415.962],[385.156,411.903],[383.967,411.903],[373.67,416.259],[372.779,417.348],[373.175,418.636],[386.443,431.804],[388.027,432.101],[406.938,424.576],[399.314,444.873]],"c":true},"ix":2},"nm":"Path 1","mn":"ADBE Vector Shape - Group","hd":false},{"ty":"fl","c":{"a":0,"k":[1,1,1,1],"ix":4},"o":{"a":0,"k":100,"ix":5},"r":1,"bm":0,"nm":"Fill 1","mn":"ADBE Vector Graphic - Fill","hd":false},{"ty":"tr","p":{"a":0,"k":[0,0],"ix":2},"a":{"a":0,"k":[0,0],"ix":1},"s":{"a":0,"k":[100,100],"ix":3},"r":{"a":0,"k":0,"ix":6},"o":{"a":0,"k":100,"ix":7},"sk":{"a":0,"k":0,"ix":4},"sa":{"a":0,"k":0,"ix":5},"nm":"Transform"}],"nm":"Group 1","np":2,"cix":2,"bm":0,"ix":1,"mn":"ADBE Vector Group","hd":false}],"ip":0,"op":288,"st":0,"bm":0},{"ddd":0,"ind":7,"ty":4,"nm":"Cloud","sr":1,"ks":{"o":{"a":0,"k":100,"ix":11},"r":{"a":0,"k":0,"ix":10},"p":{"a":1,"k":[{"i":{"x":0.833,"y":0.833},"o":{"x":0.167,"y":0.167},"t":41,"s":[333.5,67.5,0],"e":[-52.5,323.5,0],"to":[-64.333,42.667,0],"ti":[64.333,-42.667,0]},{"t":312}],"ix":2},"a":{"a":0,"k":[239.5,277.5,0],"ix":1},"s":{"a":0,"k":[100,100,100],"ix":6}},"ao":0,"shapes":[{"ty":"gr","it":[{"ind":0,"ty":"sh","ix":1,"ks":{"a":0,"k":{"i":[[7.702,0.344],[6.833,0],[2.774,-7.056],[0,-7.612],[-8.008,0],[-2.613,2.548],[-2.243,0],[-2.51,1.222],[-2.625,0],[0,8.008]],"o":[[-3.348,-5.414],[-8.041,0],[-7.458,0.599],[0,8.008],[3.938,0],[1.998,0.714],[2.979,0],[2.124,1.22],[8.008,0],[0,-7.787]],"v":[[256.154,266.033],[240,257],[222.327,269.059],[209,283.5],[223.5,298],[233.616,293.877],[240,295],[248.297,293.073],[255.5,295],[270,280.5]],"c":true},"ix":2},"nm":"Path 1","mn":"ADBE Vector Shape - Group","hd":false},{"ty":"fl","c":{"a":0,"k":[0.596078431373,0.83137254902,0.925490196078,1],"ix":4},"o":{"a":0,"k":100,"ix":5},"r":1,"bm":0,"nm":"Fill 1","mn":"ADBE Vector Graphic - Fill","hd":false},{"ty":"tr","p":{"a":0,"k":[0,0],"ix":2},"a":{"a":0,"k":[0,0],"ix":1},"s":{"a":0,"k":[100,100],"ix":3},"r":{"a":0,"k":0,"ix":6},"o":{"a":0,"k":100,"ix":7},"sk":{"a":0,"k":0,"ix":4},"sa":{"a":0,"k":0,"ix":5},"nm":"Transform"}],"nm":"Group 1","np":2,"cix":2,"bm":0,"ix":1,"mn":"ADBE Vector Group","hd":false}],"ip":0,"op":288,"st":0,"bm":0},{"ddd":0,"ind":8,"ty":4,"nm":"Wing","sr":1,"ks":{"o":{"a":0,"k":100,"ix":11},"r":{"a":0,"k":0,"ix":10},"p":{"a":1,"k":[{"i":{"x":0.4,"y":1},"o":{"x":0.6,"y":0},"t":0,"s":[131.193,121.487,0],"e":[135.193,125.487,0],"to":[0.667,0.667,0],"ti":[-0.001,-0.002,0]},{"i":{"x":0.4,"y":1},"o":{"x":0.6,"y":0},"t":86,"s":[135.193,125.487,0],"e":[131.2,121.5,0],"to":[0.001,0.002,0],"ti":[0.665,0.665,0]},{"t":288}],"ix":2},"a":{"a":0,"k":[447.443,430.737,0],"ix":1},"s":{"a":0,"k":[259.077,259.077,100],"ix":6}},"ao":0,"shapes":[{"ty":"gr","it":[{"ind":0,"ty":"sh","ix":1,"ks":{"a":0,"k":{"i":[[0.594,0.198],[0,0],[0.297,-0.099],[0,0],[0,-0.594],[-0.495,-0.297],[0,0],[-0.099,0],[-0.198,0.099],[0,0],[0,0.594]],"o":[[0,0],[-0.396,-0.099],[0,0],[-0.594,0.198],[0,0.594],[0,0],[0.198,0.099],[0.198,0],[0,0],[0.495,-0.198],[0,-0.594]],"v":[[464.67,431.467],[442.195,422.655],[441.106,422.655],[430.215,427.111],[429.324,428.497],[430.215,429.883],[452.987,438.794],[453.482,438.893],[454.076,438.794],[464.67,434.141],[465.562,432.754]],"c":true},"ix":2},"nm":"Path 1","mn":"ADBE Vector Shape - Group","hd":false},{"ty":"fl","c":{"a":0,"k":[0.7890625,0.859375,0.87109375,1],"ix":4},"o":{"a":0,"k":100,"ix":5},"r":1,"bm":0,"nm":"Fill 1","mn":"ADBE Vector Graphic - Fill","hd":false},{"ty":"tr","p":{"a":0,"k":[0,0],"ix":2},"a":{"a":0,"k":[0,0],"ix":1},"s":{"a":0,"k":[100,100],"ix":3},"r":{"a":0,"k":0,"ix":6},"o":{"a":0,"k":100,"ix":7},"sk":{"a":0,"k":0,"ix":4},"sa":{"a":0,"k":0,"ix":5},"nm":"Transform"}],"nm":"Group 1","np":2,"cix":2,"bm":0,"ix":1,"mn":"ADBE Vector Group","hd":false}],"ip":0,"op":288,"st":0,"bm":0},{"ddd":0,"ind":9,"ty":4,"nm":"BG","sr":1,"ks":{"o":{"a":0,"k":100,"ix":11},"r":{"a":0,"k":0,"ix":10},"p":{"a":0,"k":[150,150,0],"ix":2},"a":{"a":0,"k":[0,0,0],"ix":1},"s":{"a":0,"k":[100,100,100],"ix":6}},"ao":0,"shapes":[{"ty":"gr","it":[{"ty":"rc","d":1,"s":{"a":0,"k":[298.75,299.52],"ix":2},"p":{"a":0,"k":[0,0],"ix":3},"r":{"a":0,"k":0,"ix":4},"nm":"Rectangle Path 1","mn":"ADBE Vector Shape - Rect","hd":false},{"ty":"st","c":{"a":0,"k":[0,0.160784313725,0.235294132607,1],"ix":3},"o":{"a":0,"k":100,"ix":4},"w":{"a":0,"k":1,"ix":5},"lc":1,"lj":1,"ml":4,"bm":0,"nm":"Stroke 1","mn":"ADBE Vector Graphic - Stroke","hd":false},{"ty":"fl","c":{"a":0,"k":[1,0.4823529411764706,0.6745098039215687,1],"ix":4},"o":{"a":0,"k":100,"ix":5},"r":1,"bm":0,"nm":"Fill 1","mn":"ADBE Vector Graphic - Fill","hd":false},{"ty":"tr","p":{"a":0,"k":[0.375,-0.24],"ix":2},"a":{"a":0,"k":[0,0],"ix":1},"s":{"a":0,"k":[100,100],"ix":3},"r":{"a":0,"k":0,"ix":6},"o":{"a":0,"k":100,"ix":7},"sk":{"a":0,"k":0,"ix":4},"sa":{"a":0,"k":0,"ix":5},"nm":"Transform"}],"nm":"Rectangle 1","np":3,"cix":2,"bm":0,"ix":1,"mn":"ADBE Vector Group","hd":false}],"ip":0,"op":288,"st":0,"bm":0}],"markers":[]}